adeptiv_evaluator_sdk/__init__.py
adeptiv_evaluator_sdk/config.py
adeptiv_evaluator_sdk/decorator.py
adeptiv_evaluator_sdk/telemetry.py
adeptiv_evaluator_sdk/utils.py
adeptiv_ai_evaluator_sdk-1.1.11.dist-info/METADATA
adeptiv_ai_evaluator_sdk-1.1.11.dist-info/WHEEL
adeptiv_ai_evaluator_sdk-1.1.11.dist-info/top_level.txt
adeptiv_ai_evaluator_sdk-1.1.11.dist-info/RECORD
