Metadata-Version: 2.4
Name: adeptiv-ai-evaluator-sdk
Version: 1.1.11
Summary: Adeptiv GenAI tracing SDK for LLMs, agents, and AI workflows
Author-email: Adeptiv AI <contact@adeptiv-ai.com>
License: Apache-2.0
Requires-Dist: opentelemetry-api
Requires-Dist: opentelemetry-sdk
Requires-Dist: opentelemetry-exporter-otlp
Requires-Dist: opentelemetry-instrumentation-logging
Requires-Dist: opentelemetry-exporter-otlp-proto-grpc
Requires-Dist: opentelemetry-exporter-otlp-proto-http
